[
  {
    "ticker": "GC=F",
    "name": "Gold Futures",
    "ko_name": "금 선물",
    "type": "COMMODITY",
    "category": "귀금속",
    "sector": null,
    "sub_sector": null,
    "market_cap": null,
    "volume": null,
    "exchange": "COMEX",
    "currency": "USD",
    "common_ticker": "GOLD GCF",
    "mcv_id": "GC=F-USD-YAHOO",
    "source": "YAHOO"
  },
  {
    "ticker": "SI=F",
    "name": "Silver Futures",
    "ko_name": "은 선물",
    "type": "COMMODITY",
    "category": "귀금속",
    "sector": null,
    "sub_sector": null,
    "market_cap": null,
    "volume": null,
    "exchange": "COMEX",
    "currency": "USD",
    "common_ticker": "SILVER SIF",
    "mcv_id": "SI=F-USD-YAHOO",
    "source": "YAHOO"
  },
  {
    "ticker": "PL=F",
    "name": "Platinum Futures",
    "ko_name": "백금 선물",
    "type": "COMMODITY",
    "category": "귀금속",
    "sector": null,
    "sub_sector": null,
    "market_cap": null,
    "volume": null,
    "exchange": "NYMEX",
    "currency": "USD",
    "common_ticker": "PLATINUM PLF",
    "mcv_id": "PL=F-USD-YAHOO",
    "source": "YAHOO"
  },
  {
    "ticker": "PA=F",
    "name": "Palladium Futures",
    "ko_name": "팔라듐 선물",
    "type": "COMMODITY",
    "category": "귀금속",
    "sector": null,
    "sub_sector": null,
    "market_cap": null,
    "volume": null,
    "exchange": "NYMEX",
    "currency": "USD",
    "common_ticker": "PALLADIUM PAF",
    "mcv_id": "PA=F-USD-YAHOO",
    "source": "YAHOO"
  },
  {
    "ticker": "CL=F",
    "name": "Crude Oil WTI",
    "ko_name": "서부텍사스산원유(WTI) 선물",
    "type": "COMMODITY",
    "category": "에너지",
    "sector": null,
    "sub_sector": null,
    "market_cap": null,
    "volume": null,
    "exchange": "NYMEX",
    "currency": "USD",
    "common_ticker": "CRUDE OIL CLF WTI",
    "mcv_id": "CL=F-USD-YAHOO",
    "source": "YAHOO"
  },
  {
    "ticker": "BZ=F",
    "name": "Brent Crude Oil",
    "ko_name": "브렌트유 선물",
    "type": "COMMODITY",
    "category": "에너지",
    "sector": null,
    "sub_sector": null,
    "market_cap": null,
    "volume": null,
    "exchange": "ICE",
    "currency": "USD",
    "common_ticker": "BRENT CRUDE OIL BZF",
    "mcv_id": "BZ=F-USD-YAHOO",
    "source": "YAHOO"
  },
  {
    "ticker": "NG=F",
    "name": "Natural Gas",
    "ko_name": "천연가스 선물",
    "type": "COMMODITY",
    "category": "에너지",
    "sector": null,
    "sub_sector": null,
    "market_cap": null,
    "volume": null,
    "exchange": "NYMEX",
    "currency": "USD",
    "common_ticker": "NATURAL GAS NGF",
    "mcv_id": "NG=F-USD-YAHOO",
    "source": "YAHOO"
  },
  {
    "ticker": "RB=F",
    "name": "RBOB Gasoline Futures",
    "ko_name": "가솔린 선물",
    "type": "COMMODITY",
    "category": "에너지",
    "sector": null,
    "sub_sector": null,
    "market_cap": null,
    "volume": null,
    "exchange": "NYMEX",
    "currency": "USD",
    "common_ticker": "RBOB GASOLINE FUTURES RBF",
    "mcv_id": "RB=F-USD-YAHOO",
    "source": "YAHOO"
  },
  {
    "ticker": "HO=F",
    "name": "Heating Oil Futures",
    "ko_name": "난방유 선물",
    "type": "COMMODITY",
    "category": "에너지",
    "sector": null,
    "sub_sector": null,
    "market_cap": null,
    "volume": null,
    "exchange": "NYMEX",
    "currency": "USD",
    "common_ticker": "HEATING OIL FUTURE HOF",
    "mcv_id": "HO=F-USD-YAHOO",
    "source": "YAHOO"
  },
  {
    "ticker": "HG=F",
    "name": "Copper Futures",
    "ko_name": "구리 선물",
    "type": "COMMODITY",
    "category": "산업금속",
    "sector": null,
    "sub_sector": null,
    "market_cap": null,
    "volume": null,
    "exchange": "COMEX",
    "currency": "USD",
    "common_ticker": "COPPER FUTURES HGF",
    "mcv_id": "HG=F-USD-YAHOO",
    "source": "YAHOO"
  },
  {
    "ticker": "ALI=F",
    "name": "Aluminum Futures",
    "ko_name": "알루미늄 선물",
    "type": "COMMODITY",
    "category": "산업금속",
    "sector": null,
    "sub_sector": null,
    "market_cap": null,
    "volume": null,
    "exchange": "LME",
    "currency": "USD",
    "common_ticker": "ALUMINUM FUTURES ALIF",
    "mcv_id": "ALI=F-USD-YAHOO",
    "source": "YAHOO"
  },
  {
    "ticker": "ZNC=F",
    "name": "Zinc Futures",
    "ko_name": "아연 선물",
    "type": "COMMODITY",
    "category": "산업금속",
    "sector": null,
    "sub_sector": null,
    "market_cap": null,
    "volume": null,
    "exchange": "LME",
    "currency": "USD",
    "common_ticker": "ZINC FUTURES ZNCF",
    "mcv_id": "ZNC=F-USD-YAHOO",
    "source": "YAHOO"
  },
  {
    "ticker": "LED=F",
    "name": "Lead Futures",
    "ko_name": "납 선물",
    "type": "COMMODITY",
    "category": "산업금속",
    "sector": null,
    "sub_sector": null,
    "market_cap": null,
    "volume": null,
    "exchange": "LME",
    "currency": "USD",
    "common_ticker": "LEAD FUTURES LEDF",
    "mcv_id": "LED=F-USD-YAHOO",
    "source": "YAHOO"
  },
  {
    "ticker": "ZC=F",
    "name": "Corn Futures",
    "ko_name": "옥수수 선물",
    "type": "COMMODITY",
    "category": "농산물",
    "sector": null,
    "sub_sector": null,
    "market_cap": null,
    "volume": null,
    "exchange": "CBOT",
    "currency": "USD",
    "common_ticker": "CORN FUTURES ZCF",
    "mcv_id": "ZC=F-USD-YAHOO",
    "source": "YAHOO"
  },
  {
    "ticker": "ZS=F",
    "name": "Soybean Futures",
    "ko_name": "대두 선물",
    "type": "COMMODITY",
    "category": "농산물",
    "sector": null,
    "sub_sector": null,
    "market_cap": null,
    "volume": null,
    "exchange": "CBOT",
    "currency": "USD",
    "common_ticker": "SOYBEAN FUTURES ZSF",
    "mcv_id": "ZS=F-USD-YAHOO",
    "source": "YAHOO"
  },
  {
    "ticker": "ZW=F",
    "name": "Wheat Futures",
    "ko_name": "밀 선물",
    "type": "COMMODITY",
    "category": "농산물",
    "sector": null,
    "sub_sector": null,
    "market_cap": null,
    "volume": null,
    "exchange": "CBOT",
    "currency": "USD",
    "common_ticker": "WHEAT FUTURES ZWF",
    "mcv_id": "ZW=F-USD-YAHOO",
    "source": "YAHOO"
  },
  {
    "ticker": "CT=F",
    "name": "Cotton Futures",
    "ko_name": "면화 선물",
    "type": "COMMODITY",
    "category": "농산물",
    "sector": null,
    "sub_sector": null,
    "market_cap": null,
    "volume": null,
    "exchange": "ICE",
    "currency": "USD",
    "common_ticker": "COTTON FUTURES CTF",
    "mcv_id": "CT=F-USD-YAHOO",
    "source": "YAHOO"
  },
  {
    "ticker": "SB=F",
    "name": "Sugar Futures",
    "ko_name": "설탕 선물",
    "type": "COMMODITY",
    "category": "농산물",
    "sector": null,
    "sub_sector": null,
    "market_cap": null,
    "volume": null,
    "exchange": "ICE",
    "currency": "USD",
    "common_ticker": "SUGAR FUTURES SBF",
    "mcv_id": "SB=F-USD-YAHOO",
    "source": "YAHOO"
  },
  {
    "ticker": "KC=F",
    "name": "Coffee Futures",
    "ko_name": "커피 선물",
    "type": "COMMODITY",
    "category": "농산물",
    "sector": null,
    "sub_sector": null,
    "market_cap": null,
    "volume": null,
    "exchange": "ICE",
    "currency": "USD",
    "common_ticker": "COFFEE FUTURES KCF",
    "mcv_id": "KC=F-USD-YAHOO",
    "source": "YAHOO"
  },
  {
    "ticker": "OJ=F",
    "name": "Orange Juice Futures",
    "ko_name": "오렌지주스 선물",
    "type": "COMMODITY",
    "category": "농산물",
    "sector": null,
    "sub_sector": null,
    "market_cap": null,
    "volume": null,
    "exchange": "ICE",
    "currency": "USD",
    "common_ticker": "ORANGE JUICE FUTURES OJF",
    "mcv_id": "OJ=F-USD-YAHOO",
    "source": "YAHOO"
  },
  {
    "ticker": "LBS=F",
    "name": "Lumber Futures",
    "ko_name": "목재(원목) 선물",
    "type": "COMMODITY",
    "category": "농산물",
    "sector": null,
    "sub_sector": null,
    "market_cap": null,
    "volume": null,
    "exchange": "CME",
    "currency": "USD",
    "common_ticker": "LUMBER FUTURES LBSF",
    "mcv_id": "LBS=F-USD-YAHOO",
    "source": "YAHOO"
  },
  {
    "ticker": "GLD",
    "name": "SPDR Gold Shares",
    "ko_name": "금 ETF(GLD)",
    "type": "ETF",
    "category": "귀금속",
    "sector": null,
    "sub_sector": null,
    "market_cap": null,
    "volume": null,
    "exchange": "NYSE",
    "currency": "USD",
    "common_ticker": "GLD",
    "mcv_id": "GLD-USD-YAHOO",
    "source": "YAHOO"
  },
  {
    "ticker": "SLV",
    "name": "iShares Silver Trust",
    "ko_name": "은 ETF(SLV)",
    "type": "ETF",
    "category": "귀금속",
    "sector": null,
    "sub_sector": null,
    "market_cap": null,
    "volume": null,
    "exchange": "NYSE",
    "currency": "USD",
    "common_ticker": "SLV",
    "mcv_id": "SLV-USD-YAHOO",
    "source": "YAHOO"
  },
  {
    "ticker": "PPLT",
    "name": "Aberdeen Standard Physical Platinum Shares ETF",
    "ko_name": "백금 ETF(PPLT)",
    "type": "ETF",
    "category": "귀금속",
    "sector": null,
    "sub_sector": null,
    "market_cap": null,
    "volume": null,
    "exchange": "NYSE",
    "currency": "USD",
    "common_ticker": "PPLT",
    "mcv_id": "PPLT-USD-YAHOO",
    "source": "YAHOO"
  },
  {
    "ticker": "USO",
    "name": "United States Oil Fund, LP",
    "ko_name": "원유 ETF(USO)",
    "type": "ETF",
    "category": "에너지",
    "sector": null,
    "sub_sector": null,
    "market_cap": null,
    "volume": null,
    "exchange": "NYSE",
    "currency": "USD",
    "common_ticker": "USO",
    "mcv_id": "USO-USD-YAHOO",
    "source": "YAHOO"
  },
  {
    "ticker": "DBA",
    "name": "Invesco DB Agriculture Fund",
    "ko_name": "농산물 ETF(DBA)",
    "type": "ETF",
    "category": "농산물",
    "sector": null,
    "sub_sector": null,
    "market_cap": null,
    "volume": null,
    "exchange": "NYSE",
    "currency": "USD",
    "common_ticker": "DBA",
    "mcv_id": "DBA-USD-YAHOO",
    "source": "YAHOO"
  }
]